pysprite/__init__.py
pysprite/psprite.py
pysprite/pysprite.py
pysprite/test/__init__.py
pysprite/test/generate_tests.py
pysprite/test/test_pysprite.py
pysprite-1.2.1.dist-info/LICENSE.txt
pysprite-1.2.1.dist-info/METADATA
pysprite-1.2.1.dist-info/WHEEL
pysprite-1.2.1.dist-info/top_level.txt
pysprite-1.2.1.dist-info/RECORD
